zqy_utils/__init__.py
zqy_utils/collect_env_info.py
zqy_utils/cpr.py
zqy_utils/debug.py
zqy_utils/dicom.py
zqy_utils/dict.py
zqy_utils/dist_copy.py
zqy_utils/io.py
zqy_utils/plot.py
zqy_utils/point.py
zqy_utils/print.py
zqy_utils/registry.py
zqy_utils/virtual_data.py
zqy_utils/vtk.py
zqy_utils-0.2.0.dist-info/LICENSE
zqy_utils-0.2.0.dist-info/METADATA
zqy_utils-0.2.0.dist-info/WHEEL
zqy_utils-0.2.0.dist-info/top_level.txt
zqy_utils-0.2.0.dist-info/RECORD
